icu/__init__.py
icu/__main__.py
icu/component.py
icu/config.json
icu/config.py
icu/constants.py
icu/event.py
icu/fuel_monitor.py
icu/generator.py
icu/highlight.py
icu/keyhandler.py
icu/log.py
icu/main_panel.py
icu/overlay.py
icu/panel.py
icu/process.py
icu/system_monitor.py
icu/tracking.py
icu/eyetracking/__init__.py
icu/eyetracking/filter.py
icu-0.0.1.dist-info/LICENSE
icu-0.0.1.dist-info/METADATA
icu-0.0.1.dist-info/WHEEL
icu-0.0.1.dist-info/top_level.txt
icu-0.0.1.dist-info/RECORD
