Metadata-Version: 1.2
Name: icu
Version: 0.0.1
Summary: Integrated Cognitive User Assistance
Home-page: https://github.com/dicelab-rhul/ICU
Author: Benedict Wilkins
Author-email: benrjw@googlemail.co.uk
License: GNU3
Platform: UNKNOWN
Classifier: Programming Language :: Python :: 3.7
Classifier: Development Status :: 2 - Pre-Alpha
Classifier: License :: OSI Approved :: GNU General Public License v3 (GPLv3)
Classifier: Operating System :: OS Independent
Requires-Python: >=3.6
